cdlf/__init__.py
cdlf/adaptive/__init__.py
cdlf/adaptive/adaptive_cp.py
cdlf/core/__init__.py
cdlf/core/base.py
cdlf/core/cross_cp.py
cdlf/core/full_cp.py
cdlf/core/split_cp.py
cdlf/monitoring/__init__.py
cdlf/monitoring/metrics.py
cdlf/serving/__init__.py
cdlf/serving/server.py
cdlf/specialized/__init__.py
cdlf/specialized/aps.py
cdlf/specialized/cqr.py
cdlf/specialized/mondrian.py
cdlf/tf_integration/__init__.py
cdlf/tf_integration/callbacks.py
cdlf/tf_integration/layers.py
cdlf/tf_integration/wrappers.py
cdlf/utils/__init__.py
cdlf/utils/helpers.py
cdlf-0.1.1.dist-info/licenses/LICENSE
cdlf-0.1.1.dist-info/METADATA
cdlf-0.1.1.dist-info/WHEEL
cdlf-0.1.1.dist-info/top_level.txt
cdlf-0.1.1.dist-info/RECORD
