Metadata-Version: 2.4
Name: cdlf
Version: 0.1.1
Summary: Conformal Deep Learning Framework - Production-ready conformal prediction for TensorFlow
Author-email: Bora Esen <esenbora575@gmail.com>
License: MIT
Project-URL: Homepage, https://pypi.org/project/cdlf/
Project-URL: Bug Tracker, https://pypi.org/project/cdlf/
Keywords: conformal-prediction,tensorflow,machine-learning,uncertainty-quantification
Classifier: Development Status :: 3 - Alpha
Classifier: Intended Audience :: Developers
Classifier: Intended Audience :: Science/Research
Classifier: License :: OSI Approved :: MIT License
Classifier: Programming Language :: Python :: 3
Classifier: Programming Language :: Python :: 3.9
Classifier: Programming Language :: Python :: 3.10
Classifier: Programming Language :: Python :: 3.11
Classifier: Programming Language :: Python :: 3.12
Classifier: Topic :: Scientific/Engineering :: Artificial Intelligence
Classifier: Topic :: Software Development :: Libraries :: Python Modules
Requires-Python: >=3.9
License-File: LICENSE
Requires-Dist: tensorflow>=2.13.0
Requires-Dist: numpy<2.0.0,>=1.24.0
Requires-Dist: scipy>=1.10.0
Requires-Dist: scikit-learn>=1.3.0
Requires-Dist: pandas>=2.0.0
Requires-Dist: tqdm>=4.65.0
Requires-Dist: pydantic>=2.0.0
Provides-Extra: dev
Requires-Dist: pytest>=7.4.0; extra == "dev"
Requires-Dist: pytest-cov>=4.1.0; extra == "dev"
Requires-Dist: pytest-xdist>=3.3.0; extra == "dev"
Requires-Dist: hypothesis>=6.82.0; extra == "dev"
Requires-Dist: black>=23.7.0; extra == "dev"
Requires-Dist: ruff>=0.0.287; extra == "dev"
Requires-Dist: mypy>=1.5.0; extra == "dev"
Requires-Dist: pre-commit>=3.3.0; extra == "dev"
Provides-Extra: serving
Requires-Dist: fastapi>=0.103.0; extra == "serving"
Requires-Dist: uvicorn[standard]>=0.23.0; extra == "serving"
Requires-Dist: pydantic>=2.0.0; extra == "serving"
Provides-Extra: monitoring
Requires-Dist: prometheus-client>=0.17.0; extra == "monitoring"
Requires-Dist: mlflow>=2.6.0; extra == "monitoring"
Provides-Extra: docs
Requires-Dist: sphinx>=7.1.0; extra == "docs"
Requires-Dist: sphinx-rtd-theme>=1.3.0; extra == "docs"
Requires-Dist: sphinx-autodoc-typehints>=1.24.0; extra == "docs"
Provides-Extra: all
Requires-Dist: cdlf[dev,docs,monitoring,serving]; extra == "all"
Dynamic: license-file
